{
  "main": {
    "id": "eeb762c8b88debfa",
    "type": "split",
    "children": [
      {
        "id": "78c69359bea88f6a",
        "type": "tabs",
        "children": [
          {
            "id": "233eebf368e36b5f",
            "type": "leaf",
            "state": {
              "type": "image",
              "state": {
                "file": "attachments/SSRF.png"
              },
              "icon": "lucide-image",
              "title": "SSRF"
            }
          }
        ]
      }
    ],
    "direction": "vertical"
  },
  "left": {
    "id": "98d580518180e943",
    "type": "split",
    "children": [
      {
        "id": "f1bc8bcf574a93b3",
        "type": "tabs",
        "children": [
          {
            "id": "42e5c341715af5ac",
            "type": "leaf",
            "state": {
              "type": "file-explorer",
              "state": {
                "sortOrder": "alphabetical",
                "autoReveal": false
              },
              "icon": "lucide-folder-closed",
              "title": "Files"
            }
          },
          {
            "id": "c568cb46bada4a5b",
            "type": "leaf",
            "state": {
              "type": "search",
              "state": {
                "query": "",
                "matchingCase": false,
                "explainSearch": false,
                "collapseAll": false,
                "extraContext": false,
                "sortOrder": "alphabetical"
              },
              "icon": "lucide-search",
              "title": "Search"
            }
          },
          {
            "id": "85d080a0c9b7af77",
            "type": "leaf",
            "state": {
              "type": "bookmarks",
              "state": {},
              "icon": "lucide-bookmark",
              "title": "Bookmarks"
            }
          }
        ]
      }
    ],
    "direction": "horizontal",
    "width": 273.5
  },
  "right": {
    "id": "f90488d5441e502d",
    "type": "split",
    "children": [
      {
        "id": "0f7b92bd225af794",
        "type": "tabs",
        "children": [
          {
            "id": "b15bf0c5a3a68968",
            "type": "leaf",
            "state": {
              "type": "outline",
              "state": {
                "file": "attachments/SSRF.png",
                "followCursor": false,
                "showSearch": false,
                "searchQuery": ""
              },
              "icon": "lucide-list",
              "title": "Outline of SSRF"
            }
          },
          {
            "id": "21d1d2ed24367c53",
            "type": "leaf",
            "state": {
              "type": "backlink",
              "state": {
                "file": "CCNA/Section 3. Host to Host Communications.md",
                "collapseAll": false,
                "extraContext": false,
                "sortOrder": "alphabetical",
                "showSearch": false,
                "searchQuery": "",
                "backlinkCollapsed": false,
                "unlinkedCollapsed": true
              },
              "icon": "links-coming-in",
              "title": "Backlinks for Section 3. Host to Host Communications"
            }
          },
          {
            "id": "f736bd4433bf3943",
            "type": "leaf",
            "state": {
              "type": "outgoing-link",
              "state": {
                "file": "CCNA/Section 3. Host to Host Communications.md",
                "linksCollapsed": false,
                "unlinkedCollapsed": true
              },
              "icon": "links-going-out",
              "title": "Outgoing links from Section 3. Host to Host Communications"
            }
          },
          {
            "id": "14e3a2175e6003e4",
            "type": "leaf",
            "state": {
              "type": "tag",
              "state": {
                "sortOrder": "frequency",
                "useHierarchy": true,
                "showSearch": false,
                "searchQuery": ""
              },
              "icon": "lucide-tags",
              "title": "Tags"
            }
          }
        ]
      }
    ],
    "direction": "horizontal",
    "width": 373.5
  },
  "left-ribbon": {
    "hiddenItems": {
      "switcher:Open quick switcher": false,
      "graph:Open graph view": false,
      "canvas:Create new canvas": false,
      "daily-notes:Open today's daily note": false,
      "templates:Insert template": false,
      "command-palette:Open command palette": false,
      "obsidian-git:Open Git source control": false,
      "obsidian-to-anki-plugin:Obsidian_to_Anki - Scan Vault": false
    }
  },
  "active": "233eebf368e36b5f",
  "lastOpenFiles": [
    "attachments/URL.png",
    "attachments/Diffie Hellman.png",
    "attachments/DB Table Example.png",
    "Home Lab/Projects.md",
    "Home Lab/Notes.md",
    "THM Notes/7. Jr Penetration Tester/5. Network Security.md",
    "THM Notes/7. Jr Penetration Tester/10. Nmap The Basics.md",
    "CEH/9. Cryptography.md",
    "CEH/8. Cloud Computing.md",
    "CEH/7. Mobile Platform, IoT, and OT Hacking.md",
    "CEH/6. Wireless Network Hacking.md",
    "CEH/5. Web App Hacking.md",
    "CEH/4. Network and Perimeter Hacking.md",
    "CEH/3. System Hacking Phases and Attack Techniques.md",
    "THM Notes/2. Cyber Security 101/4. Cryptography/1. Cryptography Basics.md",
    "THM Notes/2. Cyber Security 101/4. Cryptography/2. Public Key Cryptography Basics.md",
    "THM Notes/2. Cyber Security 101/4. Cryptography/3. Hashing Basics.md",
    "THM Notes/4. Web Fundamentals/2. Introduction to Web Hacking/10. SQL Injection.md",
    "THM Notes/2. Cyber Security 101/6. Web Hacking/3. SQL Fundamentals.md",
    "THM Notes/1. Pre Security/How The Web Works/3. How Websites Work.md",
    "CCNA/Section 4. The Cisco IOS Operating System.md",
    "THM Notes/1. Pre Security/How The Web Works/2. HTTP In Detail.md",
    "CCNA/Section 3. Host to Host Communications.md",
    "THM Notes/4. Web Fundamentals/2. Introduction to Web Hacking/7. Intro to SSRF.md",
    "THM Notes/1. Pre Security/How The Web Works/1. DNS in Detail.md",
    "THM Notes/4. Web Fundamentals/1. How The Web Works/How The Web Works.md",
    "THM Notes/4. Web Fundamentals/2. Introduction to Web Hacking/6. File Inclusion.md",
    "THM Notes/4. Web Fundamentals/2. Introduction to Web Hacking/5. IDOR.md",
    "CCNA/OCB",
    "CCNA/Neil Anderson",
    "THM Notes/4. Web Fundamentals/2. Web Fundamentals",
    "THM Notes/4. Web Fundamentals/3. Burp Suite",
    "attachments/DBMS Example.png",
    "attachments/Pasted image 20250501211442.png",
    "attachments/Pasted image 20250501211149.png",
    "attachments/Pasted image 20250501204246.png",
    "attachments/Pasted image 20250430195055.png",
    "attachments/Pasted image 20250430194629.png",
    "attachments/Pasted image 20250430194004.png",
    "attachments/Pasted image 20250430193937.png",
    "THM Notes/4. Web Fundamentals/2. Introduction to Web Hacking",
    "THM Notes/4. Web Fundamentals/1. How The Web Works",
    "THM Notes/3. Complete Beginner/7. Basic Computer Exploitation",
    "THM Notes/3. Complete Beginner/6. Shell and Privilege Escalation",
    "THM Notes/3. Complete Beginner/5. Windows Exploitation Basics",
    "THM Notes/3. Complete Beginner/4. Cryptography",
    "Untitled.canvas"
  ]
}